LICENSE
README.rst
flog/__init__.py
flog/flog.py
flog/tests/__init__.py
flog/tests/test_get_logger.py
flog/tests/test_log_call.py
flog-0.3.1.dist-info/LICENSE
flog-0.3.1.dist-info/METADATA
flog-0.3.1.dist-info/WHEEL
flog-0.3.1.dist-info/RECORD
