Metadata-Version: 2.1
Name: flog
Version: 0.3.1
Summary: Fast access to some simple python logging tricks
Home-page: https://github.com/mitgr81/flog
License: MIT
Author: Chris McGraw
Author-email: mitgr81+flog@mitgr81.com
Requires-Python: >=3.9,<4.0
Classifier: Development Status :: 4 - Beta
Classifier: Intended Audience :: Developers
Classifier: Intended Audience :: System Administrators
Classifier: License :: OSI Approved :: MIT License
Classifier: Operating System :: OS Independent
Classifier: Programming Language :: Python :: 3
Classifier: Programming Language :: Python :: 3.9
Classifier: Programming Language :: Python :: 3.10
Classifier: Programming Language :: Python :: 3.11
Classifier: Programming Language :: Python :: 3.12
Classifier: Topic :: System :: Logging
Project-URL: Repository, https://github.com/mitgr81/flog
